CHANGELOG.txt
LICENCE.txt
MANIFEST.in
README.txt
setup.py
halfdan/__init__.py
halfdan.egg-info/PKG-INFO
halfdan.egg-info/SOURCES.txt
halfdan.egg-info/dependency_links.txt
halfdan.egg-info/top_level.txt