Metadata-Version: 1.1
Name: halfdan
Version: 0.0.1
Summary: This Halfdan from Denmark`s Lib
Home-page: UNKNOWN
Author: Halfdan Lund Hahn
Author-email: gamerhalfdan@gmail.com
License: MIT
Keywords: calculator
Platform: UNKNOWN
Classifier: Development Status :: 5 - Production/Stable
Classifier: Intended Audience :: Education
Classifier: Operating System :: Microsoft :: Windows :: Windows 10
Classifier: License :: OSI Approved :: MIT License
Classifier: Programming Language :: Python :: 3
